adbutils/__init__.py
adbutils/__main__.py
adbutils/_adb.py
adbutils/_deprecated.py
adbutils/_device.py
adbutils/_device_base.py
adbutils/_interfaces.py
adbutils/_proto.py
adbutils/_utils.py
adbutils/_version.py
adbutils/errors.py
adbutils/install.py
adbutils/pidcat.py
adbutils/screenrecord.py
adbutils/screenshot.py
adbutils/shell.py
adbutils/sync.py
adbutils/binaries/README.md
adbutils/binaries/__init__.py
adbutils/binaries/adb
adbutils-2.10.2.dist-info/AUTHORS
adbutils-2.10.2.dist-info/LICENSE
adbutils-2.10.2.dist-info/METADATA
adbutils-2.10.2.dist-info/WHEEL
adbutils-2.10.2.dist-info/pbr.json
adbutils-2.10.2.dist-info/top_level.txt
adbutils-2.10.2.dist-info/RECORD
