Metadata-Version: 2.1
Name: adbutils
Version: 2.10.2
Summary: Pure Python Adb Library
Home-page: https://github.com/openatx/adbutils
Author: codeskyblue
Author-email: codeskyblue@gmail.com
License: MIT
Platform: UNKNOWN
Classifier: Development Status :: 4 - Beta
Classifier: Environment :: Console
Classifier: Intended Audience :: Developers
Classifier: Operating System :: POSIX
Classifier: Programming Language :: Python :: 3
Classifier: Programming Language :: Python :: 3.8
Classifier: Programming Language :: Python :: 3.9
Classifier: Programming Language :: Python :: 3.10
Classifier: Topic :: Software Development :: Libraries :: Python Modules
Classifier: Topic :: Software Development :: Testing
Requires-Python: >=3.8
License-File: LICENSE
License-File: AUTHORS
